{
	"namespace": "vrp",
	"vrp_sidemenu": {
		"$vrpAddon": true,
		"modifications": [
			{
				"array_name": "controls",
				"operation": "insert_back",
				"value": [
					{
						"template_button@sidemenu_button": {
							"$toggle_view_binding_name": "template_toggle",
							"$glyph_texture": "textures/vrp/addons-template/icon",
							"$glyph_color_texture": "textures/vrp/addons-template/icon",
							"$button_text": "vanillaRaytraced.addons.template",
							"$toggle_group_forced_index": 1000x (DONT FORGET TO CHANGE THE x)
						}
					}
				]
			}
		]
	},
	"vrp_content": {
		"modifications": [
			{
				"array_name": "controls",
				"operation": "insert_back",
				"value": [
					{
						"template@vrp.presentation": {
							"$id": "template_toggle",
							"$icon": "textures/vrp/addons-template/icon",
							"$desc": "vanillaRaytraced.addons.template.description",
							"$text": "template_text"
						}
					}
				]
			}
		]
	},
	"template_text": {
		"controls": [
			{
				"rp_title@menu_text": {
					"font_scale_factor": 1.2,
					"text": "vanillaRaytraced.addons.template.by"
				}
			},
			{
				"rp@menu_text": {
					"text": "/§dMaze§5Wave\n\n"
				}
			},
			{
				"license_title@menu_text": {
					"font_scale_factor": 1.2,
					"text": "vanillaRaytraced.addons.template.license.title"
				}
			},
			{
				"license@vrp.qa_answer": {
					"text": "vanillaRaytraced.addons.template.license"
				}
			},
			{ "license_gap@menu_text": { "size": [6, 6] } },
			{
				"changes_title@menu_text": {
					"font_scale_factor": 1.2,
					"text": "vanillaRaytraced.addons.template.changes"
				}
			},
			{
				"changes1-0@vrp.qa_answer": {
					"text": "vanillaRaytraced.addons.template.changes.1.0"
				}
			}
		]
	}
}